pyapa/__init__.py
pyapa/__main__.py
pyapa/main.py
pyapa/pyapa.py
pyapa-0.2.1.dist-info/DESCRIPTION.rst
pyapa-0.2.1.dist-info/METADATA
pyapa-0.2.1.dist-info/RECORD
pyapa-0.2.1.dist-info/WHEEL
pyapa-0.2.1.dist-info/entry_points.txt
pyapa-0.2.1.dist-info/metadata.json
pyapa-0.2.1.dist-info/top_level.txt
