Metadata-Version: 2.0
Name: pyapa
Version: 0.2.1
Summary: A Python module for checking APA style in writing
Home-page: https://github.com/keeferrourke/pyapa
Author: Keefer Rourke
Author-email: mail@krourke.org
License: ISC
Keywords: pyapa apa style-check writing
Platform: UNKNOWN
Classifier: Development Status :: 3 - Alpha
Classifier: Environment :: Console
Classifier: Intended Audience :: Education
Classifier: Topic :: Utilities
Classifier: License :: OSI Approved :: ISC License (ISCL)
Classifier: Programming Language :: Python :: 3
Classifier: Programming Language :: Python :: 3.3
Classifier: Programming Language :: Python :: 3.4
Classifier: Programming Language :: Python :: 3.5
